imddata-0.2.0.dist-info/METADATA
imddata-0.2.0.dist-info/WHEEL
imddata-0.2.0.dist-info/entry_points.txt
imddata-0.2.0.dist-info/licenses/LICENSE
imddata.py
imddata-0.2.0.dist-info/RECORD
