Metadata-Version: 2.1
Name: imddata
Version: 0.2.0
Summary: Download IMD Gridded Data
Author-Email: Prajeesh Ag <prajeeshag@gmail.com>
License: MIT License
Classifier: Programming Language :: Python :: 3
Classifier: Programming Language :: Python :: 3 :: Only
Classifier: Programming Language :: Python :: 3.12
Classifier: Programming Language :: Python :: 3.13
Classifier: Programming Language :: Python :: 3.14
Project-URL: homepage, https://github.com/prajeeshag/imddata
Project-URL: repository, https://github.com/prajeeshag/imddata
Project-URL: documentation, https://github.com/prajeeshag/imddata
Requires-Python: >=3.12
Requires-Dist: netcdf4>=1.7.3
Requires-Dist: numpy>=2.3.5
Requires-Dist: pandas>=2.3.3
Requires-Dist: requests>=2.32.5
Requires-Dist: typer>=0.20.0
Requires-Dist: xarray>=2025.12.0
